{"action":"CAUTIOUS","components":{"market_gate":{"contribution":-7.5,"score":25},"prediction":{"contribution":0,"spy_bullish":50.0},"regime":{"contribution":0,"regime":"neutral"},"risk":{"contribution":-10,"level":"High"},"sector_phase":{"contribution":-5,"phase":"Late Cycle"}},"score":28,"timing":"WAIT","top_picks":[],"warnings":["APO is in critical drawdown: -27.1% from peak","AMD is in critical drawdown: -23.3% from peak","APH is in critical drawdown: -24.4% from peak","ALGN drawdown warning: -12.7% from peak"]}
